nbdev_hellow_world/__init__.py
nbdev_hellow_world/_modidx.py
nbdev_hellow_world/card.py
nbdev_hellow_world/deck.py
nbdev_hellow_world-0.0.2.dist-info/LICENSE
nbdev_hellow_world-0.0.2.dist-info/METADATA
nbdev_hellow_world-0.0.2.dist-info/WHEEL
nbdev_hellow_world-0.0.2.dist-info/entry_points.txt
nbdev_hellow_world-0.0.2.dist-info/top_level.txt
nbdev_hellow_world-0.0.2.dist-info/RECORD
