Metadata-Version: 2.1
Name: nbdev-hellow-world
Version: 0.0.2
Summary: Just a quick tutorial for nbdev
Home-page: https://github.com/chsafouane/nbdev-hellow-world
Author: Safouane Chergui
Author-email: 106234065+schergui-thefork@users.noreply.github.com
License: Apache Software License 2.0
Keywords: nbdev jupyter notebook python
Classifier: Development Status :: 4 - Beta
Classifier: Intended Audience :: Developers
Classifier: Natural Language :: English
Classifier: Programming Language :: Python :: 3.7
Classifier: Programming Language :: Python :: 3.8
Classifier: Programming Language :: Python :: 3.9
Classifier: Programming Language :: Python :: 3.10
Classifier: License :: OSI Approved :: Apache Software License
Requires-Python: >=3.7
License-File: LICENSE
Provides-Extra: dev
